{
  "categorias": [
    {
      "id": 1,
      "titulo": "Categoria1",
      "cor": "#4848c0",
      "link_extra": {
        "text": "Descrição da Categoria",
        "url": "/"
      }
    },{
      "id": 2,
      "titulo": "Categoria2",
      "cor": "#5e5eaa",
      "link_extra": {
        "text": "Descrição da Categoria",
        "url": "/"
      }
    },{
      "id": 3,
      "titulo": "Categoria3",
      "cor": "#8282c8",
      "link_extra": {
        "text": "Descrição da Categoria",
        "url": "/"
      }
    }
   ],
  "videos": [
    {
      "id": 1,
      "categoriaId": 1,
      "titulo": "Dúvidas para escolher sua alimentação na quarentena?",
      "url": "https://www.youtube.com/watch?v=-jveWcwVOhM"
    },{
      "id": 2,
      "categoriaId": 2,
      "titulo": "Tucker e Echo com comidinhas novas.",
      "url": "https://www.youtube.com/watch?v=cOm5iA5TwgI"
    },{
      "id": 3,
      "categoriaId": 3,
      "titulo": "Tucker e Echo com comidinhas novas.",
      "url": "https://www.youtube.com/watch?v=cOm5iA5TwgI"
    },{
      "id": 4,
      "categoriaId": 1,
      "titulo": "Tucker e Echo com comidinhas novas.",
      "url": "https://www.youtube.com/watch?v=cOm5iA5TwgI"
    }
  ]
}